autonomie_celery/__init__.py
autonomie_celery/conf.py
autonomie_celery/exception.py
autonomie_celery/mail.py
autonomie_celery/models.py
autonomie_celery/schedulers/__init__.py
autonomie_celery/schedulers/tasks.py
autonomie_celery/tasks/__init__.py
autonomie_celery/tasks/accounting_measure_compute.py
autonomie_celery/tasks/accounting_parser.py
autonomie_celery/tasks/csv_import.py
autonomie_celery/tasks/export.py
autonomie_celery/tasks/task.py
autonomie_celery/tasks/utils.py
endi_celery/__init__.py
endi_celery/conf.py
endi_celery/exception.py
endi_celery/mail.py
endi_celery/models.py
endi_celery/schedulers/__init__.py
endi_celery/schedulers/tasks.py
endi_celery/tasks/__init__.py
endi_celery/tasks/accounting_measure_compute.py
endi_celery/tasks/accounting_parser.py
endi_celery/tasks/csv_import.py
endi_celery/tasks/export.py
endi_celery/tasks/task.py
endi_celery/tasks/utils.py
autonomie_celery-4.3.8.dist-info/LICENSE.txt
autonomie_celery-4.3.8.dist-info/METADATA
autonomie_celery-4.3.8.dist-info/WHEEL
autonomie_celery-4.3.8.dist-info/entry_points.txt
autonomie_celery-4.3.8.dist-info/top_level.txt
autonomie_celery-4.3.8.dist-info/RECORD
