Metadata-Version: 2.1
Name: autonomie-celery
Version: 4.3.8
Summary: autonomie_celery
Home-page: https://github.com/CroissanceCommune/autonomie_base
Author: Majerti
Author-email: equipe@majerti.fr
License: GPLv3
Keywords: web wsgi bfg pylons pyramid celery
Platform: UNKNOWN
Classifier: License :: OSI Approved :: GNU General Public License v3 (GPLv3)
Classifier: Programming Language :: Python
Classifier: Framework :: Pyramid
Classifier: Topic :: Internet :: WWW/HTTP
Classifier: Topic :: Internet :: WWW/HTTP :: WSGI :: Application
Requires-Dist: celery (==4.0.2)
Requires-Dist: pyramid-celery (==3.0.0)
Requires-Dist: billiard (==3.5.0.2)
Requires-Dist: kombu (==4.0.2)
Requires-Dist: redis (==2.10.5)
Requires-Dist: sylk-parser (==0.3.3)
